README.rst
setup.py
more_or_less/__init__.py
more_or_less/buffered_input.py
more_or_less/count_plugin.py
more_or_less/fixed_size_screen.py
more_or_less/help_plugin.py
more_or_less/input.py
more_or_less/line_count_plugin.py
more_or_less/more_page_builder.py
more_or_less/more_plugin.py
more_or_less/more_plugins.py
more_or_less/one_line_plugin.py
more_or_less/one_page_plugin.py
more_or_less/output.py
more_or_less/page.py
more_or_less/page_builder.py
more_or_less/page_of_height.py
more_or_less/page_wrapper.py
more_or_less/paginator.py
more_or_less/quit_plugin.py
more_or_less/repeat_plugin.py
more_or_less/repeatable_mixin.py
more_or_less/screen_dimensions.py
more_or_less/search_plugin.py
more_or_less/terminal_input.py
more_or_less/terminal_screen.py
more_or_less/wrapped_page.py
more_or_less.egg-info/PKG-INFO
more_or_less.egg-info/SOURCES.txt
more_or_less.egg-info/dependency_links.txt
more_or_less.egg-info/top_level.txt